{"world":1,"level":5,"midgrounds":[{"gridX":0,"gridY":96,"type":2},{"gridX":60,"gridY":96,"type":0},{"gridX":92,"gridY":96,"type":2},{"gridX":212,"gridY":96,"type":0},{"gridX":244,"gridY":96,"type":1},{"gridX":540,"gridY":96,"type":2},{"gridX":612,"gridY":96,"type":1},{"gridX":672,"gridY":96,"type":0},{"gridX":736,"gridY":96,"type":2},{"gridX":832,"gridY":96,"type":0},{"gridX":876,"gridY":96,"type":1},{"gridX":916,"gridY":96,"type":2},{"gridX":1196,"gridY":96,"type":2},{"gridX":1252,"gridY":96,"type":1},{"gridX":1300,"gridY":96,"type":2},{"gridX":1376,"gridY":96,"type":0},{"gridX":1428,"gridY":96,"type":0},{"gridX":1488,"gridY":96,"type":2},{"gridX":1584,"gridY":96,"type":1},{"gridX":1548,"gridY":96,"type":0},{"gridX":1960,"gridY":96,"type":2},{"gridX":2124,"gridY":96,"type":0},{"gridX":2160,"gridY":96,"type":0},{"gridX":564,"gridY":96,"type":0},{"gridX":724,"gridY":96,"type":17},{"gridX":725,"gridY":112,"type":18},{"gridX":733,"gridY":114,"type":18},{"gridX":754,"gridY":122,"type":17},{"gridX":743,"gridY":122,"type":18},{"gridX":782,"gridY":140,"type":17},{"gridX":770,"gridY":132,"type":18},{"gridX":793,"gridY":148,"type":18},{"gridX":763,"gridY":121,"type":18},{"gridX":805,"gridY":96,"type":17},{"gridX":797,"gridY":102,"type":18},{"gridX":809,"gridY":111,"type":18},{"gridX":816,"gridY":117,"type":18},{"gridX":826,"gridY":119,"type":17},{"gridX":844,"gridY":111,"type":18},{"gridX":843,"gridY":133,"type":17},{"gridX":833,"gridY":131,"type":18},{"gridX":810,"gridY":153,"type":18},{"gridX":822,"gridY":143,"type":18},{"gridX":908,"gridY":126,"type":17},{"gridX":898,"gridY":111,"type":17},{"gridX":888,"gridY":123,"type":18},{"gridX":908,"gridY":109,"type":18},{"gridX":897,"gridY":96,"type":17},{"gridX":865,"gridY":136,"type":17},{"gridX":887,"gridY":136,"type":17},{"gridX":884,"gridY":144,"type":18},{"gridX":917,"gridY":96,"type":17},{"gridX":922,"gridY":113,"type":18},{"gridX":875,"gridY":96,"type":17},{"gridX":881,"gridY":108,"type":18},{"gridX":860,"gridY":104,"type":18},{"gridX":799,"gridY":162,"type":18},{"gridX":1543,"gridY":96,"type":17},{"gridX":1538,"gridY":108,"type":18},{"gridX":1549,"gridY":121,"type":17},{"gridX":1545,"gridY":96,"type":18},{"gridX":1553,"gridY":109,"type":18},{"gridX":1566,"gridY":122,"type":17},{"gridX":1558,"gridY":131,"type":18},{"gridX":1581,"gridY":117,"type":18},{"gridX":1591,"gridY":108,"type":17},{"gridX":1592,"gridY":96,"type":17},{"gridX":1582,"gridY":101,"type":18},{"gridX":1600,"gridY":112,"type":18},{"gridX":1608,"gridY":122,"type":18},{"gridX":1617,"gridY":130,"type":18},{"gridX":1620,"gridY":118,"type":18},{"gridX":1546,"gridY":138,"type":18},{"gridX":1873,"gridY":96,"type":17},{"gridX":1863,"gridY":112,"type":18},{"gridX":1880,"gridY":114,"type":17},{"gridX":1868,"gridY":128,"type":18},{"gridX":1893,"gridY":96,"type":17},{"gridX":1898,"gridY":113,"type":18},{"gridX":1884,"gridY":129,"type":18},{"gridX":1875,"gridY":141,"type":18},{"gridX":1899,"gridY":125,"type":18},{"gridX":1893,"gridY":138,"type":18},{"gridX":761,"gridY":135,"type":17},{"gridX":1913,"gridY":96,"type":17},{"gridX":1933,"gridY":97,"type":17},{"gridX":1955,"gridY":96,"type":17},{"gridX":1976,"gridY":96,"type":17},{"gridX":1998,"gridY":96,"type":17},{"gridX":2017,"gridY":96,"type":17},{"gridX":1935,"gridY":118,"type":17},{"gridX":1924,"gridY":198,"type":17},{"gridX":1955,"gridY":118,"type":17},{"gridX":1976,"gridY":118,"type":17},{"gridX":1997,"gridY":118,"type":17},{"gridX":2018,"gridY":118,"type":17},{"gridX":2038,"gridY":96,"type":17},{"gridX":2038,"gridY":118,"type":17},{"gridX":2059,"gridY":96,"type":17},{"gridX":2059,"gridY":118,"type":17},{"gridX":1865,"gridY":96,"type":6},{"gridX":1893,"gridY":96,"type":6},{"gridX":619,"gridY":96,"type":16},{"gridX":210,"gridY":96,"type":16},{"gridX":49,"gridY":96,"type":15},{"gridX":170,"gridY":96,"type":14},{"gridX":395,"gridY":96,"type":13},{"gridX":469,"gridY":96,"type":14},{"gridX":492,"gridY":96,"type":13},{"gridX":1898,"gridY":140,"type":18},{"gridX":1941,"gridY":132,"type":18},{"gridX":1942,"gridY":193,"type":17},{"gridX":1943,"gridY":142,"type":18},{"gridX":1726,"gridY":101,"type":18},{"gridX":1714,"gridY":96,"type":17},{"gridX":1720,"gridY":112,"type":17},{"gridX":1705,"gridY":96,"type":18},{"gridX":1701,"gridY":140,"type":18},{"gridX":1714,"gridY":128,"type":17},{"gridX":1727,"gridY":144,"type":18},{"gridX":1732,"gridY":128,"type":18},{"gridX":1736,"gridY":142,"type":17},{"gridX":1851,"gridY":138,"type":17},{"gridX":1789,"gridY":158,"type":18},{"gridX":1806,"gridY":143,"type":18},{"gridX":1795,"gridY":138,"type":17},{"gridX":1835,"gridY":137,"type":18},{"gridX":1832,"gridY":148,"type":18},{"gridX":1813,"gridY":152,"type":18},{"gridX":1823,"gridY":142,"type":18},{"gridX":1779,"gridY":145,"type":17},{"gridX":1765,"gridY":149,"type":18},{"gridX":1746,"gridY":144,"type":18},{"gridX":1755,"gridY":153,"type":18},{"gridX":1795,"gridY":124,"type":18},{"gridX":1800,"gridY":103,"type":18},{"gridX":1795,"gridY":111,"type":18},{"gridX":1799,"gridY":96,"type":17},{"gridX":1736,"gridY":154,"type":18},{"gridX":1886,"gridY":178,"type":17},{"gridX":1907,"gridY":178,"type":17},{"gridX":1929,"gridY":178,"type":17},{"gridX":1893,"gridY":156,"type":17},{"gridX":1931,"gridY":156,"type":17},{"gridX":1912,"gridY":161,"type":17},{"gridX":1902,"gridY":198,"type":17},{"gridX":1924,"gridY":216,"type":17},{"gridX":1882,"gridY":189,"type":18},{"gridX":1889,"gridY":201,"type":18},{"gridX":1884,"gridY":214,"type":18},{"gridX":1902,"gridY":216,"type":17},{"gridX":1887,"gridY":226,"type":18}],"grounds":[{"gridX":0,"gridY":0,"type":25},{"gridX":648,"gridY":0,"type":26},{"gridX":8,"gridY":0,"type":28},{"gridX":136,"gridY":0,"type":28},{"gridX":264,"gridY":0,"type":28},{"gridX":392,"gridY":0,"type":28},{"gridX":680,"gridY":0,"type":28},{"gridX":808,"gridY":0,"type":28},{"gridX":1832,"gridY":0,"type":28},{"gridX":1960,"gridY":0,"type":28},{"gridX":2088,"gridY":0,"type":28},{"gridX":936,"gridY":0,"type":28},{"gridX":1064,"gridY":0,"type":28},{"gridX":1192,"gridY":0,"type":28},{"gridX":1320,"gridY":0,"type":28},{"gridX":1448,"gridY":0,"type":28},{"gridX":520,"gridY":0,"type":28},{"gridX":1576,"gridY":0,"type":28},{"gridX":1704,"gridY":0,"type":28},{"gridX":2216,"gridY":0,"type":29}],"pits":[{"gridX":292,"gridY":0,"type":33},{"gridX":954,"gridY":0,"type":33},{"gridX":1405,"gridY":0,"type":30},{"gridX":1629,"gridY":0,"type":33},{"gridX":1429,"gridY":37,"type":34},{"gridX":1453,"gridY":37,"type":35},{"gridX":1485,"gridY":37,"type":35},{"gridX":1517,"gridY":37,"type":35},{"gridX":1549,"gridY":37,"type":35},{"gridX":1581,"gridY":37,"type":35},{"gridX":1613,"gridY":37,"type":36}],"exitGrounds":[],"holes":[],"foregroundObjects":[{"gridX":1952,"gridY":96,"type":12},{"gridX":184,"gridY":96,"type":20},{"gridX":710,"gridY":96,"type":58},{"gridX":705,"gridY":101,"type":60},{"gridX":803,"gridY":118,"type":61},{"gridX":842,"gridY":122,"type":60},{"gridX":895,"gridY":146,"type":60},{"gridX":918,"gridY":146,"type":60},{"gridX":930,"gridY":163,"type":61},{"gridX":910,"gridY":138,"type":59},{"gridX":918,"gridY":96,"type":55},{"gridX":894,"gridY":96,"type":55},{"gridX":887,"gridY":96,"type":53},{"gridX":941,"gridY":96,"type":56},{"gridX":220,"gridY":144,"type":51},{"gridX":204,"gridY":156,"type":50},{"gridX":236,"gridY":156,"type":50},{"gridX":252,"gridY":144,"type":51},{"gridX":202,"gridY":96,"type":53},{"gridX":210,"gridY":96,"type":56},{"gridX":220,"gridY":96,"type":52},{"gridX":220,"gridY":112,"type":52},{"gridX":220,"gridY":128,"type":52},{"gridX":252,"gridY":96,"type":52},{"gridX":252,"gridY":112,"type":52},{"gridX":252,"gridY":128,"type":52},{"gridX":268,"gridY":120,"type":50},{"gridX":284,"gridY":120,"type":50},{"gridX":1369,"gridY":96,"type":52},{"gridX":1369,"gridY":112,"type":51},{"gridX":1353,"gridY":124,"type":50},{"gridX":1352,"gridY":96,"type":53},{"gridX":1359,"gridY":96,"type":55},{"gridX":1382,"gridY":96,"type":54},{"gridX":1393,"gridY":96,"type":56},{"gridX":1454,"gridY":96,"type":52},{"gridX":1454,"gridY":112,"type":51},{"gridX":1448,"gridY":96,"type":55},{"gridX":1440,"gridY":96,"type":53},{"gridX":1471,"gridY":96,"type":56},{"gridX":1625,"gridY":134,"type":60},{"gridX":1537,"gridY":149,"type":60},{"gridX":1536,"gridY":96,"type":54},{"gridX":1528,"gridY":96,"type":53},{"gridX":1548,"gridY":96,"type":56},{"gridX":1869,"gridY":136,"type":59},{"gridX":1870,"gridY":144,"type":60},{"gridX":1885,"gridY":141,"type":59},{"gridX":1874,"gridY":166,"type":58},{"gridX":1868,"gridY":175,"type":60},{"gridX":1954,"gridY":215,"type":59},{"gridX":1887,"gridY":152,"type":59},{"gridX":1799,"gridY":160,"type":59},{"gridX":1863,"gridY":139,"type":59},{"gridX":1007,"gridY":78,"type":62},{"gridX":1080,"gridY":80,"type":62},{"gridX":1955,"gridY":204,"type":60},{"gridX":1990,"gridY":142,"type":60},{"gridX":1950,"gridY":184,"type":59},{"gridX":1950,"gridY":138,"type":59},{"gridX":1948,"gridY":154,"type":59},{"gridX":1947,"gridY":198,"type":59},{"gridX":2006,"gridY":137,"type":59},{"gridX":1964,"gridY":158,"type":59},{"gridX":1964,"gridY":129,"type":59},{"gridX":1997,"gridY":130,"type":59},{"gridX":1957,"gridY":186,"type":60},{"gridX":1961,"gridY":145,"type":59},{"gridX":2015,"gridY":126,"type":59},{"gridX":2027,"gridY":119,"type":59},{"gridX":2035,"gridY":130,"type":59},{"gridX":2020,"gridY":133,"type":60},{"gridX":2043,"gridY":123,"type":59},{"gridX":2054,"gridY":125,"type":59},{"gridX":2063,"gridY":133,"type":59},{"gridX":2045,"gridY":137,"type":60},{"gridX":753,"gridY":145,"type":60},{"gridX":795,"gridY":168,"type":60},{"gridX":1978,"gridY":136,"type":63},{"gridX":1952,"gridY":170,"type":63},{"gridX":1976,"gridY":150,"type":59},{"gridX":1944,"gridY":211,"type":59},{"gridX":1941,"gridY":223,"type":59},{"gridX":1946,"gridY":227,"type":59},{"gridX":1693,"gridY":0,"type":63},{"gridX":1715,"gridY":0,"type":63},{"gridX":1688,"gridY":8,"type":59},{"gridX":1705,"gridY":20,"type":63},{"gridX":1690,"gridY":26,"type":60},{"gridX":1711,"gridY":26,"type":60},{"gridX":1724,"gridY":13,"type":59},{"gridX":1704,"gridY":74,"type":60},{"gridX":1702,"gridY":149,"type":60},{"gridX":1714,"gridY":143,"type":59},{"gridX":1720,"gridY":190,"type":60},{"gridX":1796,"gridY":166,"type":60},{"gridX":1794,"gridY":146,"type":59},{"gridX":1832,"gridY":7,"type":4},{"gridX":1600,"gridY":96,"type":53},{"gridX":1608,"gridY":96,"type":54},{"gridX":1620,"gridY":96,"type":56},{"gridX":1828,"gridY":7,"type":3},{"gridX":1846,"gridY":7,"type":5},{"gridX":1687,"gridY":91,"type":61},{"gridX":1719,"gridY":155,"type":59},{"gridX":1722,"gridY":166,"type":63},{"gridX":1722,"gridY":178,"type":59},{"gridX":1833,"gridY":12,"type":21},{"gridX":1884,"gridY":232,"type":63},{"gridX":1906,"gridY":232,"type":63},{"gridX":1924,"gridY":232,"type":63},{"gridX":1938,"gridY":232,"type":59},{"gridX":1911,"gridY":219,"type":59},{"gridX":1873,"gridY":232,"type":59},{"gridX":1151,"gridY":81,"type":62},{"gridX":131,"gridY":96,"type":64}],"midBossForegroundObjects":[],"endBossForegroundObjects":[],"countHissWithMinas":[{"gridX":1920,"gridY":96}],"endBossSnakes":[],"enemies":[{"gridX":848,"gridY":96,"type":8},{"gridX":940,"gridY":188,"type":3},{"gridX":1272,"gridY":96,"type":9},{"gridX":367,"gridY":96,"type":3},{"gridX":500,"gridY":110,"type":3},{"gridX":1933,"gridY":96,"type":4},{"gridX":455,"gridY":108,"type":3},{"gridX":1508,"gridY":96,"type":8},{"gridX":1568,"gridY":96,"type":6},{"gridX":408,"gridY":103,"type":3},{"gridX":251,"gridY":176,"type":3},{"gridX":256,"gridY":164,"type":8}],"collectibles":[{"gridX":704,"gridY":128,"type":0},{"gridX":1484,"gridY":124,"type":0},{"gridX":1492,"gridY":116,"type":0},{"gridX":1500,"gridY":108,"type":0},{"gridX":712,"gridY":128,"type":0},{"gridX":720,"gridY":128,"type":0},{"gridX":284,"gridY":220,"type":1},{"gridX":728,"gridY":128,"type":0},{"gridX":756,"gridY":116,"type":0},{"gridX":764,"gridY":112,"type":0},{"gridX":772,"gridY":108,"type":0},{"gridX":808,"gridY":128,"type":0},{"gridX":816,"gridY":128,"type":0},{"gridX":824,"gridY":128,"type":0},{"gridX":862,"gridY":152,"type":0},{"gridX":846,"gridY":152,"type":0},{"gridX":854,"gridY":152,"type":0},{"gridX":1637,"gridY":163,"type":0},{"gridX":911,"gridY":176,"type":0},{"gridX":919,"gridY":176,"type":0},{"gridX":928,"gridY":176,"type":0},{"gridX":936,"gridY":176,"type":0},{"gridX":944,"gridY":176,"type":0},{"gridX":1786,"gridY":113,"type":1},{"gridX":960,"gridY":184,"type":0},{"gridX":968,"gridY":184,"type":0},{"gridX":1000,"gridY":180,"type":0},{"gridX":1040,"gridY":172,"type":0},{"gridX":1048,"gridY":172,"type":0},{"gridX":1088,"gridY":164,"type":0},{"gridX":1080,"gridY":164,"type":0},{"gridX":1120,"gridY":156,"type":0},{"gridX":1128,"gridY":156,"type":0},{"gridX":1168,"gridY":148,"type":0},{"gridX":1160,"gridY":148,"type":0},{"gridX":612,"gridY":104,"type":0},{"gridX":596,"gridY":104,"type":0},{"gridX":604,"gridY":104,"type":0},{"gridX":668,"gridY":112,"type":0},{"gridX":672,"gridY":120,"type":0},{"gridX":676,"gridY":128,"type":0},{"gridX":133,"gridY":111,"type":0},{"gridX":137,"gridY":120,"type":0},{"gridX":142,"gridY":129,"type":0},{"gridX":200,"gridY":164,"type":0},{"gridX":206,"gridY":172,"type":0},{"gridX":1508,"gridY":106,"type":0},{"gridX":1442,"gridY":148,"type":0},{"gridX":1434,"gridY":154,"type":0},{"gridX":1448,"gridY":138,"type":0},{"gridX":1410,"gridY":159,"type":0},{"gridX":1455,"gridY":131,"type":0},{"gridX":1464,"gridY":131,"type":0},{"gridX":1472,"gridY":131,"type":0},{"gridX":188,"gridY":124,"type":0},{"gridX":192,"gridY":132,"type":0},{"gridX":196,"gridY":140,"type":0},{"gridX":1517,"gridY":111,"type":0},{"gridX":1526,"gridY":121,"type":0},{"gridX":1536,"gridY":125,"type":0},{"gridX":1547,"gridY":126,"type":0},{"gridX":1558,"gridY":124,"type":0},{"gridX":1399,"gridY":157,"type":0},{"gridX":1423,"gridY":159,"type":0},{"gridX":1573,"gridY":116,"type":0},{"gridX":1575,"gridY":129,"type":0},{"gridX":1578,"gridY":140,"type":0},{"gridX":1580,"gridY":149,"type":0},{"gridX":1584,"gridY":159,"type":0},{"gridX":1623,"gridY":181,"type":0},{"gridX":1611,"gridY":182,"type":0},{"gridX":1631,"gridY":172,"type":0},{"gridX":1008,"gridY":180,"type":0},{"gridX":976,"gridY":184,"type":0},{"gridX":1016,"gridY":180,"type":0},{"gridX":1056,"gridY":172,"type":0},{"gridX":1096,"gridY":164,"type":0},{"gridX":1136,"gridY":156,"type":0},{"gridX":1176,"gridY":148,"type":0},{"gridX":1590,"gridY":169,"type":0},{"gridX":1599,"gridY":176,"type":0},{"gridX":1676,"gridY":142,"type":0},{"gridX":1709,"gridY":101,"type":0},{"gridX":1814,"gridY":112,"type":0},{"gridX":1682,"gridY":135,"type":0},{"gridX":1688,"gridY":127,"type":0},{"gridX":1699,"gridY":112,"type":0},{"gridX":1743,"gridY":117,"type":0},{"gridX":1716,"gridY":100,"type":0},{"gridX":1724,"gridY":108,"type":0},{"gridX":1732,"gridY":116,"type":0},{"gridX":1754,"gridY":116,"type":0},{"gridX":1772,"gridY":116,"type":0},{"gridX":1917,"gridY":106,"type":0},{"gridX":1794,"gridY":113,"type":0},{"gridX":1888,"gridY":106,"type":0},{"gridX":1804,"gridY":112,"type":0},{"gridX":1908,"gridY":106,"type":0},{"gridX":1764,"gridY":116,"type":0},{"gridX":1898,"gridY":106,"type":0},{"gridX":1703,"gridY":105,"type":0},{"gridX":1214,"gridY":100,"type":1},{"gridX":1694,"gridY":120,"type":0},{"gridX":1452,"gridY":50,"type":2},{"gridX":1496,"gridY":49,"type":2},{"gridX":1536,"gridY":49,"type":2},{"gridX":1572,"gridY":48,"type":2},{"gridX":1606,"gridY":49,"type":2},{"gridX":1836,"gridY":27,"type":3},{"gridX":1879,"gridY":202,"type":3},{"gridX":1737,"gridY":219,"type":2},{"gridX":1749,"gridY":234,"type":0},{"gridX":1760,"gridY":238,"type":0},{"gridX":1781,"gridY":234,"type":0},{"gridX":1772,"gridY":238,"type":0},{"gridX":1795,"gridY":218,"type":0},{"gridX":1799,"gridY":208,"type":0},{"gridX":1802,"gridY":200,"type":0},{"gridX":1804,"gridY":192,"type":0},{"gridX":1812,"gridY":192,"type":0},{"gridX":1811,"gridY":201,"type":0},{"gridX":1789,"gridY":227,"type":0}],"jons":[{"gridX":20,"gridY":96}],"extraForegroundObjects":[],"foregroundCoverObjects":[{"gridX":1886,"gridY":92,"type":3}],"markers":[{"gridX":2228,"gridY":0,"type":1}]}